pcuf/__init__.py
pcuf/containers.py
pcuf/file.py
pcuf/functions.py
pcuf/warnings.py
pcuf/ext/__init__.py
pcuf/ext/click.py
pcuf/ext/excel.py
pcuf/time/__init__.py
pcuf/time/epoch.py
pcuf-0.1.9.dist-info/AUTHORS.rst
pcuf-0.1.9.dist-info/LICENSE
pcuf-0.1.9.dist-info/METADATA
pcuf-0.1.9.dist-info/WHEEL
pcuf-0.1.9.dist-info/top_level.txt
pcuf-0.1.9.dist-info/RECORD
