Metadata-Version: 2.1
Name: pcuf
Version: 0.1.9
Summary: A personal collection of useful and frequently used Python functions.
Home-page: https://github.com/git-albertomarin/pcuf
Author: Alberto J. Marin
Author-email: alberto@ajmar.in
License: BSD license
Keywords: pcuf
Platform: UNKNOWN
Classifier: Development Status :: 2 - Pre-Alpha
Classifier: Intended Audience :: Developers
Classifier: License :: OSI Approved :: BSD License
Classifier: Natural Language :: English
Classifier: Programming Language :: Python :: 3.6
Classifier: Programming Language :: Python :: 3.7
Requires-Dist: xlrd (>=1.2.0)
Requires-Dist: pandas (>=0.24.1)
Requires-Dist: requests (>=2.21.0)
Requires-Dist: click (>=7.0)
Requires-Dist: openpyxl (>=2.5.12)
